google/api_core/__init__.py
google/api_core/_rest_streaming_base.py
google/api_core/bidi.py
google/api_core/client_info.py
google/api_core/client_logging.py
google/api_core/client_options.py
google/api_core/datetime_helpers.py
google/api_core/exceptions.py
google/api_core/extended_operation.py
google/api_core/general_helpers.py
google/api_core/grpc_helpers.py
google/api_core/grpc_helpers_async.py
google/api_core/iam.py
google/api_core/operation.py
google/api_core/operation_async.py
google/api_core/page_iterator.py
google/api_core/page_iterator_async.py
google/api_core/path_template.py
google/api_core/protobuf_helpers.py
google/api_core/py.typed
google/api_core/rest_helpers.py
google/api_core/rest_streaming.py
google/api_core/rest_streaming_async.py
google/api_core/retry_async.py
google/api_core/timeout.py
google/api_core/universe.py
google/api_core/version.py
google/api_core/version_header.py
google/api_core/future/__init__.py
google/api_core/future/_helpers.py
google/api_core/future/async_future.py
google/api_core/future/base.py
google/api_core/future/polling.py
google/api_core/gapic_v1/__init__.py
google/api_core/gapic_v1/client_info.py
google/api_core/gapic_v1/config.py
google/api_core/gapic_v1/config_async.py
google/api_core/gapic_v1/method.py
google/api_core/gapic_v1/method_async.py
google/api_core/gapic_v1/routing_header.py
google/api_core/operations_v1/__init__.py
google/api_core/operations_v1/abstract_operations_base_client.py
google/api_core/operations_v1/abstract_operations_client.py
google/api_core/operations_v1/operations_async_client.py
google/api_core/operations_v1/operations_client.py
google/api_core/operations_v1/operations_client_config.py
google/api_core/operations_v1/operations_rest_client_async.py
google/api_core/operations_v1/pagers.py
google/api_core/operations_v1/pagers_async.py
google/api_core/operations_v1/pagers_base.py
google/api_core/operations_v1/transports/__init__.py
google/api_core/operations_v1/transports/base.py
google_api_core-2.25.0.dist-info/LICENSE
google_api_core-2.25.0.dist-info/METADATA
google_api_core-2.25.0.dist-info/WHEEL
google_api_core-2.25.0.dist-info/top_level.txt
google_api_core-2.25.0.dist-info/RECORD
