Metadata-Version: 2.1
Name: google-api-core
Version: 2.25.0
Summary: Google API client core library
Author-email: Google LLC <googleapis-packages@google.com>
License: Apache 2.0
Project-URL: Documentation, https://googleapis.dev/python/google-api-core/latest/
Project-URL: Repository, https://github.com/googleapis/python-api-core
Classifier: Development Status :: 5 - Production/Stable
Classifier: Intended Audience :: Developers
Classifier: License :: OSI Approved :: Apache Software License
Classifier: Programming Language :: Python
Classifier: Programming Language :: Python :: 3
Classifier: Programming Language :: Python :: 3.7
Classifier: Programming Language :: Python :: 3.8
Classifier: Programming Language :: Python :: 3.9
Classifier: Programming Language :: Python :: 3.10
Classifier: Programming Language :: Python :: 3.11
Classifier: Programming Language :: Python :: 3.12
Classifier: Programming Language :: Python :: 3.13
Classifier: Operating System :: OS Independent
Classifier: Topic :: Internet
Requires-Python: >=3.7
License-File: LICENSE
Requires-Dist: googleapis-common-protos<2.0.0,>=1.56.2
Requires-Dist: protobuf!=3.20.0,!=3.20.1,!=4.21.0,!=4.21.1,!=4.21.2,!=4.21.3,!=4.21.4,!=4.21.5,<7.0.0,>=3.19.5
Requires-Dist: proto-plus<2.0.0,>=1.22.3
Requires-Dist: proto-plus<2.0.0,>=1.25.0; python_version >= "3.13"
Requires-Dist: google-auth<3.0.0,>=2.14.1
Requires-Dist: requests<3.0.0,>=2.18.0
Provides-Extra: async-rest
Requires-Dist: google-auth[aiohttp]<3.0.0,>=2.35.0; extra == "async-rest"
Provides-Extra: grpc
Requires-Dist: grpcio<2.0.0,>=1.33.2; extra == "grpc"
Requires-Dist: grpcio<2.0.0,>=1.49.1; python_version >= "3.11" and extra == "grpc"
Requires-Dist: grpcio-status<2.0.0,>=1.33.2; extra == "grpc"
Requires-Dist: grpcio-status<2.0.0,>=1.49.1; python_version >= "3.11" and extra == "grpc"
Provides-Extra: grpcgcp
Requires-Dist: grpcio-gcp<1.0.0,>=0.2.2; extra == "grpcgcp"
Provides-Extra: grpcio-gcp
Requires-Dist: grpcio-gcp<1.0.0,>=0.2.2; extra == "grpcio-gcp"
